voicetransformer/__init__.py
voicetransformer/__main__.py
voicetransformer/voice.py
voicetransformer-0.0.3.dist-info/LICENSE
voicetransformer-0.0.3.dist-info/METADATA
voicetransformer-0.0.3.dist-info/WHEEL
voicetransformer-0.0.3.dist-info/top_level.txt
voicetransformer-0.0.3.dist-info/RECORD
