Metadata-Version: 2.1
Name: voicetransformer
Version: 0.0.3
Summary: A wrapper over WORLD's Python wrapper to facilitate voice transformation
Home-page: https://github.com/egaudrain/voicetransformer
Author: Etienne gaudrain
Author-email: egaudrain@gmail.com
License: UNKNOWN
Project-URL: Bug Tracker, https://github.com/egaudrain/voicetransformer
Platform: UNKNOWN
Classifier: Programming Language :: Python :: 3
Classifier: License :: OSI Approved :: MIT License
Classifier: Operating System :: OS Independent
Requires-Python: >=3.6
License-File: LICENSE
Requires-Dist: pyworld
Requires-Dist: scipy
Requires-Dist: soundfile
